[{"content":"DATOS PERSONALES NOMBRE Y APELLIDO: NORMA AMANDA ABDALA DE MATARAZZO\nDISTRITO AL QUE REPRESENTA: SANTIAGO DEL ESTERO\nINTERBLOQUE: FRENTE DE TODOS\nPROFESIÓN: DOCENTE\nFECHA DE NAC.: 13/04/1948\nPERÍODO: 10/12/2017 - 09/12/2021\nAUSENCIAS: 155, DE UN TOTAL DE 1148 VOTACIONES.\n https://www.hcdn.gob.ar/diputados/nabdaladem\n DATOS LEGISLATIVOS COMISIONES:\n FAMILIAS, NIÑEZ Y JUVENTUDES (Secretaria) ASUNTOS MUNICIPALES (Vocal) DE LAS PERSONAS MAYORES (Vocal) EDUCACION (Vocal) PREVISION Y SEGURIDAD SOCIAL (Vocal)   https://www.hcdn.gob.ar/diputados/nabdaladem/comisiones.html\n ESTADÍSTICAS DE PROYECTOS PRESENTADOS AUTOR: 104 Proyectos\nCOAUTOR: 378 Proyectos\n https://www.hcdn.gob.ar/diputados/nabdaladem/listadodeproy.html\n ","description":"NORMA AMANDA ABDALA DE MATARAZZO","id":0,"section":"candidatos","tags":null,"title":"NORMA AMANDA ABDALA DE MATARAZZO","uri":"https://lavidrieradelcongreso.com.ar/es/candidatos/mi-primer-post/"},{"content":"probando\nlorem akdha fhbakhfakjshfkahsfkja hkjha hakjshf akjfhg ajfhas fjhajf hajfhga jhfakjfhakjsfhkajshf kjfhagkjajsf\n","description":"","id":1,"section":"","tags":null,"title":"Contacto","uri":"https://lavidrieradelcongreso.com.ar/es/contacto/"}]